LICENSE
MANIFEST.in
README.md
setup.py
NlpToolkit_Util_Cy.egg-info/PKG-INFO
NlpToolkit_Util_Cy.egg-info/SOURCES.txt
NlpToolkit_Util_Cy.egg-info/dependency_links.txt
NlpToolkit_Util_Cy.egg-info/top_level.txt
Util/FileUtils.c
Util/FileUtils.pxd
Util/FileUtils.pyx
Util/Interval.c
Util/Interval.pyx
Util/Permutation.c
Util/Permutation.pyx
Util/RandomArray.c
Util/RandomArray.pxd
Util/RandomArray.pyx
Util/Subset.c
Util/Subset.pxd
Util/Subset.pyx
Util/SubsetFromList.c
Util/SubsetFromList.pyx
Util/Swap.c
Util/Swap.pyx
Util/__init__.c
Util/__init__.py
nlptoolkit_util_cy.egg-info/PKG-INFO
nlptoolkit_util_cy.egg-info/SOURCES.txt
nlptoolkit_util_cy.egg-info/dependency_links.txt
nlptoolkit_util_cy.egg-info/top_level.txt