Metadata-Version: 2.1
Name: nlptoolkit-util-cy
Version: 1.0.12
Summary: Simple Utils
Home-page: https://github.com/StarlangSoftware/Util-Cy
Author: olcaytaner
Author-email: olcay.yildiz@ozyegin.edu.tr
License-File: LICENSE
